rockblock.cp313-win32.pyd
rockblock9704/__init__.py
rockblock9704/rockblock9704.py
rockblock9704-0.1.28.dist-info/licenses/LICENSE
rockblock9704-0.1.28.dist-info/METADATA
rockblock9704-0.1.28.dist-info/WHEEL
rockblock9704-0.1.28.dist-info/top_level.txt
rockblock9704-0.1.28.dist-info/RECORD
