Metadata-Version: 2.4
Name: rockblock9704
Version: 0.1.28
Summary: RockBLOCK 9704 serial tools
Project-URL: About, https://www.groundcontrol.com/product/rockblock-9704/
Project-URL: Docs, https://docs.groundcontrol.com/iot/rockblock-9704
Project-URL: Examples, https://github.com/rock7/RockBLOCK-9704/tree/master/examples/python
Requires-Python: >=3.10
License-File: LICENSE
Dynamic: license-file
